MANIFEST.in
README
requirements.txt
setup.py
ceilometer_publisher_vaultaire/__init__.py
ceilometer_publisher_vaultaire/vaultaire.py
ceilometer_publisher_vaultaire.egg-info/PKG-INFO
ceilometer_publisher_vaultaire.egg-info/SOURCES.txt
ceilometer_publisher_vaultaire.egg-info/dependency_links.txt
ceilometer_publisher_vaultaire.egg-info/entry_points.txt
ceilometer_publisher_vaultaire.egg-info/not-zip-safe
ceilometer_publisher_vaultaire.egg-info/requires.txt
ceilometer_publisher_vaultaire.egg-info/top_level.txt