Metadata-Version: 1.1
Name: ceilometer-publisher-vaultaire
Version: 0.0.4
Summary: A publisher plugin for Ceilometer that outputs to Vaultaire
Home-page: https://github.com/anchor/ceilometer-publisher-vaultaire
Author: Barney Desmond
Author-email: engineering@anchor.net.au
License: UNKNOWN
Platform: UNKNOWN
Classifier: Development Status :: 3 - Alpha
Classifier: Topic :: Utilities
Classifier: License :: OSI Approved :: Apache Software License
